bns_nlp_engine-1.0.0.dist-info/licenses/LICENSE
bnsnlp/__init__.py
bnsnlp/__version__.py
bnsnlp/py.typed
bnsnlp/api/__init__.py
bnsnlp/api/service.py
bnsnlp/classify/__init__.py
bnsnlp/classify/base.py
bnsnlp/classify/turkish.py
bnsnlp/cli/__init__.py
bnsnlp/cli/main.py
bnsnlp/core/__init__.py
bnsnlp/core/config.py
bnsnlp/core/exceptions.py
bnsnlp/core/pipeline.py
bnsnlp/core/registry.py
bnsnlp/core/types.py
bnsnlp/embed/__init__.py
bnsnlp/embed/base.py
bnsnlp/embed/cohere.py
bnsnlp/embed/huggingface.py
bnsnlp/embed/openai.py
bnsnlp/preprocess/__init__.py
bnsnlp/preprocess/base.py
bnsnlp/preprocess/cleaner.py
bnsnlp/preprocess/deasciifier.py
bnsnlp/preprocess/lemmatizer.py
bnsnlp/preprocess/normalizer.py
bnsnlp/preprocess/splitter.py
bnsnlp/preprocess/stopwords.py
bnsnlp/preprocess/tokenizer.py
bnsnlp/preprocess/tokenizer_advanced.py
bnsnlp/preprocess/turkish.py
bnsnlp/preprocess/turkish_advanced.py
bnsnlp/search/__init__.py
bnsnlp/search/base.py
bnsnlp/search/faiss.py
bnsnlp/search/pinecone.py
bnsnlp/search/qdrant.py
bnsnlp/utils/__init__.py
bnsnlp/utils/logging.py
bnsnlp/utils/performance.py
bnsnlp/utils/security.py
bnsnlp/utils/telemetry.py
bns_nlp_engine-1.0.0.dist-info/METADATA
bns_nlp_engine-1.0.0.dist-info/WHEEL
bns_nlp_engine-1.0.0.dist-info/entry_points.txt
bns_nlp_engine-1.0.0.dist-info/top_level.txt
bns_nlp_engine-1.0.0.dist-info/RECORD
